{"name":"ShellTODO","tagline":"”a simple TODO list manager directly from shell”","body":"#Installing\r\n\r\n```bash\r\n~$ git clone https://github.com/adrian7/shelltodo.git\r\n~$ cd shelltodo\r\n~$ mv shelltodo.py todo\r\n~$ chmod +x todo\r\n```\r\n#Usage\r\n```\r\n~$ todo -a \"upgrade machine to Debian 7\"\r\n~$ todo -a \"upgrade php to 5.7\"\r\n~$ todo -a \"check apache logs\"\r\n~$ todo -s\r\n~$ todo -m 1\r\n~$ todo -d 2\r\n```","google":"","note":"Don't delete this file! It's used internally to help with page regeneration."}